README.md
setup.py
logstats/__init__.py
logstats/base.py
logstats/thread.py
logstats.egg-info/PKG-INFO
logstats.egg-info/SOURCES.txt
logstats.egg-info/dependency_links.txt
logstats.egg-info/top_level.txt