Metadata-Version: 1.1
Name: logstats
Version: 0.3.0
Summary: A module to collect and display stats for long running processes
Home-page: https://github.com/vrde/logstats
Author: Alberto Granzotto
Author-email: agranzot@gmail.com
License: MIT
Platform: UNKNOWN
Classifier: Development Status :: 3 - Alpha
Classifier: Intended Audience :: Developers
Classifier: Topic :: Software Development :: Build Tools
Classifier: License :: OSI Approved :: MIT License
Classifier: Programming Language :: Python :: 3
